colab_alarm/__init__.py
colab_alarm/alarm.py
colab_alarm-0.1.3.dist-info/licenses/LICENSE
colab_alarm-0.1.3.dist-info/METADATA
colab_alarm-0.1.3.dist-info/WHEEL
colab_alarm-0.1.3.dist-info/top_level.txt
colab_alarm-0.1.3.dist-info/RECORD
