Metadata-Version: 2.4
Name: colab-alarm
Version: 0.1.3
Summary: Simple audio alarm for Google Colab notebooks
Author-email: Nidhi Parab <nidhiparabmail@gmail.com>
License: MIT
Project-URL: Homepage, https://github.com/nidhiparab/colab-alarm
Project-URL: Bug Tracker, https://github.com/nidhiparab/colab-alarm/issues
Project-URL: Documentation, https://github.com/nidhiparab/colab-alarm#readme
Keywords: colab,jupyter,notification,alarm
Classifier: Programming Language :: Python :: 3
Classifier: License :: OSI Approved :: MIT License
Classifier: Operating System :: OS Independent
Requires-Python: >=3.7
License-File: LICENSE
Requires-Dist: numpy
Requires-Dist: ipython
Dynamic: license-file
